bmaclient/__init__.py
bmaclient/bind.py
bmaclient/client.py
bmaclient/deprecations.py
bmaclient/encoder.py
bmaclient/exceptions.py
bmaclient/langhelpers.py
bmaclient/models.py
bmaclient/request.py
bmaclient/utils.py
bmaclient/version.py
bmaclient-0.15.1.dist-info/LICENSE
bmaclient-0.15.1.dist-info/METADATA
bmaclient-0.15.1.dist-info/WHEEL
bmaclient-0.15.1.dist-info/top_level.txt
bmaclient-0.15.1.dist-info/RECORD
