Metadata-Version: 2.1
Name: bmaclient
Version: 0.15.1
Summary: BPPTKG Monitoring APIs Python Client
Home-page: https://github.com/bpptkg/bmaclient
Author: BPPTKG
Author-email: bpptkg@esdm.go.id
License: MIT
Classifier: Development Status :: 5 - Production/Stable
Classifier: Environment :: Console
Classifier: Operating System :: POSIX :: Linux
Classifier: Intended Audience :: Science/Research
Classifier: Natural Language :: Indonesian
Classifier: Programming Language :: Python :: 3.6
Classifier: Programming Language :: Python :: 3.7
Classifier: Programming Language :: Python :: 3.8
Classifier: Programming Language :: Python :: 3.9
Requires-Python: >=3.5
License-File: LICENSE
Requires-Dist: httplib2 (>=0.9)
Requires-Dist: six (>=1.8.0)
